{
  "settings": {
    "name": "Joe Design",
    "real_name": "يوسف",
    "bio_ar": "هدفي إني أخلي منتجاتك تظهر بأحسن شكل يشد ناس.",
    "phone": "01124527286",
    "whatsapp": "201124527286",
    "email": "yfhhdrbkwuig@gmail.com",
    "instagram": "https://www.instagram.com/kaboos645/",
    "tiktok": "",
    "facebook": "",
    "behance": "",
    "stats": {
      "projects": "60",
      "clients": "6",
      "years": "1.5",
      "brands": "0"
    }
  },
  "work_sections": [
    {
      "id": "restaurants",
      "label": "تصميم المطاعم",
      "images": [
        "https://i.ibb.co/XZXPJY6R/2.png",
        "https://i.ibb.co/fVGhmsCn/7.png",
        "https://i.ibb.co/wTnKs4s/9.png"
      ]
    },
    {
      "id": "confectionery",
      "label": "تصميم الحلواني",
      "images": []
    },
    {
      "id": "perfumes",
      "label": "تصميم العطور",
      "images": []
    },
    {
      "id": "clothing",
      "label": "تصميم الملابس",
      "images": []
    },
    {
      "id": "menus",
      "label": "تصميم المنيوهات",
      "images": []
    }
  ],
  "videos": {
    "sections": [
      {
        "id": "behind",
        "label": "كواليس أعمالي",
        "items": [
          {
            "title": "كوليس تصميم عطر",
            "url": "https://youtube.com/shorts/THoa5CqXcJw?feature=share"
          }
        ]
      },
      {
        "id": "ai",
        "label": "فيديوهات AI",
        "items": []
      },
      {
        "id": "motion",
        "label": "موشن جرافيك",
        "items": []
      },
      {
        "id": "editing",
        "label": "فيديو إديتينج",
        "items": []
      }
    ]
  },
  "clients": [
    {
      "name": "حلواني خير",
      "logo": "https://i.ibb.co/nsjM008M/479737131-122205210080233573-7254976098471849338-n.jpg"
    }
  ],
  "testimonials": []
}